dugaire/__init__.py
dugaire/dugaire.py
dugaire/pkg/__init__.py
dugaire/pkg/app/__init__.py
dugaire/pkg/app/app.py
dugaire/pkg/apt/__init__.py
dugaire/pkg/apt/apt.py
dugaire/pkg/apt/template/apt.dockerfile.j2
dugaire/pkg/cli/__init__.py
dugaire/pkg/cli/cli.py
dugaire/pkg/docker/__init__.py
dugaire/pkg/docker/docker.py
dugaire/pkg/docker/template/base.dockerfile.j2
dugaire/pkg/http/__init__.py
dugaire/pkg/http/http.py
dugaire/pkg/pip3/__init__.py
dugaire/pkg/pip3/pip3.py
dugaire/pkg/pip3/template/pip3.dockerfile.j2
dugaire/pkg/util/__init__.py
dugaire/pkg/util/util.py
dugaire/pkg/with_kubectl/__init__.py
dugaire/pkg/with_kubectl/with_kubectl.py
dugaire/pkg/with_kubectl/template/kubectl.dockerfile.j2
dugaire/pkg/with_terraform/__init__.py
dugaire/pkg/with_terraform/with_terraform.py
dugaire/pkg/with_terraform/template/terraform.dockerfile.j2
dugaire/pkg/with_velero/__init__.py
dugaire/pkg/with_velero/with_velero.py
dugaire/pkg/with_velero/template/velero.dockerfile.j2
dugaire-0.0.15.dist-info/LICENSE
dugaire-0.0.15.dist-info/METADATA
dugaire-0.0.15.dist-info/WHEEL
dugaire-0.0.15.dist-info/entry_points.txt
dugaire-0.0.15.dist-info/top_level.txt
dugaire-0.0.15.dist-info/RECORD
