Metadata-Version: 2.1
Name: dugaire
Version: 0.0.15
Summary: Build Docker images with custom packages for local development, testing and daily tasks.
Home-page: https://github.com/tadeugr/dugaire
Author: Tadeu Granemann
License: Apache License, Version 2.0
Classifier: License :: OSI Approved :: Apache Software License
Classifier: Programming Language :: Python
Classifier: Programming Language :: Python :: 3
License-File: LICENSE
Requires-Dist: click (==8.1.3)
Requires-Dist: click-completion (==0.5.2)
Requires-Dist: docker (==5.0.3)
Requires-Dist: Jinja2 (==3.1.2)
Requires-Dist: rich (==12.5.1)
